[
  {
    "ContainingType": "AMS.Controllers.AuthController",
    "Method": "Authenticate",
    "RelativePath": "Auth/Authenticate",
    "HttpMethod": "POST",
    "IsController": true,
    "Order": 0,
    "Parameters": [
      {
        "Name": "username",
        "Type": "System.String",
        "IsRequired": false
      },
      {
        "Name": "password",
        "Type": "System.String",
        "IsRequired": false
      }
    ],
    "ReturnTypes": []
  },
  {
    "ContainingType": "AMS.Controllers.UsersController",
    "Method": "GetPermissions",
    "RelativePath": "Users/GetPermissions",
    "HttpMethod": "GET",
    "IsController": true,
    "Order": 0,
    "Parameters": [
      {
        "Name": "userid",
        "Type": "System.Int64",
        "IsRequired": false
      }
    ],
    "ReturnTypes": []
  },
  {
    "ContainingType": "AMS.Controllers.UsersController",
    "Method": "GetRoles",
    "RelativePath": "Users/GetRoles",
    "HttpMethod": "GET",
    "IsController": true,
    "Order": 0,
    "Parameters": [
      {
        "Name": "userid",
        "Type": "System.Int64",
        "IsRequired": false
      }
    ],
    "ReturnTypes": []
  },
  {
    "ContainingType": "AMS.Controllers.UsersController",
    "Method": "GetUsersByName",
    "RelativePath": "Users/GetUsersByName",
    "HttpMethod": "GET",
    "IsController": true,
    "Order": 0,
    "Parameters": [
      {
        "Name": "UsersName",
        "Type": "System.String",
        "IsRequired": false
      }
    ],
    "ReturnTypes": []
  },
  {
    "ContainingType": "AMS.Controllers.UsersController",
    "Method": "Register",
    "RelativePath": "Users/Register",
    "HttpMethod": "POST",
    "IsController": true,
    "Order": 0,
    "Parameters": [
      {
        "Name": "request",
        "Type": "DLL.Models.Users.InsertUserRequest",
        "IsRequired": true
      }
    ],
    "ReturnTypes": []
  },
  {
    "ContainingType": "AMS.Controllers.WeatherForecastController",
    "Method": "Get",
    "RelativePath": "WeatherForecast",
    "HttpMethod": "GET",
    "IsController": true,
    "Order": 0,
    "Parameters": [],
    "ReturnTypes": [
      {
        "Type": "System.Collections.Generic.IEnumerable\u00601[[AMS.WeatherForecast, AMS, Version=1.0.0.0, Culture=neutral, PublicKeyToken=null]]",
        "MediaTypes": [
          "text/plain",
          "application/json",
          "text/json"
        ],
        "StatusCode": 200
      }
    ],
    "EndpointName": "GetWeatherForecast"
  }
]